baseline_package/__init__.py
baseline_package/cli.py
baseline_package/config.py
baseline_package/constants.py
baseline_package/exceptions.py
baseline_package/globals.py
baseline_package/main.py
baseline_package/notify.py
baseline_package-0.0.1rc2.dist-info/LICENSE.md
baseline_package-0.0.1rc2.dist-info/METADATA
baseline_package-0.0.1rc2.dist-info/WHEEL
baseline_package-0.0.1rc2.dist-info/entry_points.txt
baseline_package-0.0.1rc2.dist-info/top_level.txt
baseline_package-0.0.1rc2.dist-info/RECORD
