Metadata-Version: 2.1
Name: baseline-package
Version: 0.0.1rc2
Summary: A nice description will go here
Home-page: https://github.com/GreyTeamToolbox/baseline-package
Author: Wolf Software
Author-email: pypi@wolfsoftware.com
Project-URL: Source, https://github.com/GreyTeamToolbox/baseline-package
Project-URL: Tracker, https://github.com/GreyTeamToolbox/baseline-package/issues/
Project-URL: Documentation, https://github.com/GreyTeamToolbox/baseline-package
Project-URL: Funding, https://ko-fi.com/wolfsoftware
Project-URL: Say Thanks!, https://github.com/sponsors/TGWolf
Classifier: Environment :: Console
Classifier: Intended Audience :: Developers
Classifier: Programming Language :: Python :: 3
Classifier: License :: OSI Approved :: MIT License
Classifier: Operating System :: OS Independent
Classifier: Topic :: Software Development
Requires-Python: >=3.9
License-File: LICENSE.md
Requires-Dist: colorama ==0.4.6
Requires-Dist: setuptools ==69.5.1
